odoo/addons/sm_partago_invoicing/__init__.py
odoo/addons/sm_partago_invoicing/__manifest__.py
odoo/addons/sm_partago_invoicing/controllers/__init__.py
odoo/addons/sm_partago_invoicing/controllers/invoice_controller.py
odoo/addons/sm_partago_invoicing/controllers/report_controller.py
odoo/addons/sm_partago_invoicing/email_tmpl/invoice_email.xml
odoo/addons/sm_partago_invoicing/email_tmpl/invoice_email_header.xml
odoo/addons/sm_partago_invoicing/email_tmpl/invoice_report.xml
odoo/addons/sm_partago_invoicing/email_tmpl/sale_order.xml
odoo/addons/sm_partago_invoicing/email_tmpl/sale_order_header.xml
odoo/addons/sm_partago_invoicing/models/__init__.py
odoo/addons/sm_partago_invoicing/models/batch_type_enum.py
odoo/addons/sm_partago_invoicing/models/models_reservation_calculator.py
odoo/addons/sm_partago_invoicing/models/models_sm_company.py
odoo/addons/sm_partago_invoicing/models/models_sm_invoice.py
odoo/addons/sm_partago_invoicing/models/models_sm_invoice_line.py
odoo/addons/sm_partago_invoicing/models/models_sm_invoice_report.py
odoo/addons/sm_partago_invoicing/models/models_sm_invoice_report_wizard.py
odoo/addons/sm_partago_invoicing/models/models_sm_member.py
odoo/addons/sm_partago_invoicing/models/models_sm_res_config_settings.py
odoo/addons/sm_partago_invoicing/models/models_sm_teletac.py
odoo/addons/sm_partago_invoicing/models/models_smp_batch_reservation_compute.py
odoo/addons/sm_partago_invoicing/models/models_smp_batch_reservation_compute_wizard.py
odoo/addons/sm_partago_invoicing/models/models_smp_locals_groups_config.py
odoo/addons/sm_partago_invoicing/models/models_smp_report_reservation_compute.py
odoo/addons/sm_partago_invoicing/models/models_smp_reservation_compute.py
odoo/addons/sm_partago_invoicing/report/contact.xml
odoo/addons/sm_partago_invoicing/report/invoice_report.xml
odoo/addons/sm_partago_invoicing/report/saleorder_report.xml
odoo/addons/sm_partago_invoicing/report/sm_invoice_report.xml
odoo11_addon_sm_partago_invoicing-11.0.0.0.2.dist-info/METADATA
odoo11_addon_sm_partago_invoicing-11.0.0.0.2.dist-info/WHEEL
odoo11_addon_sm_partago_invoicing-11.0.0.0.2.dist-info/top_level.txt
odoo11_addon_sm_partago_invoicing-11.0.0.0.2.dist-info/RECORD
